{"assam":{"name":"Assam"},"ladakh":{"name":"Ladakh"},"andhra-pradesh":{"name":"Andhra Pradesh"},"manipur":{"name":"Manipur"},"madhya-pradesh":{"name":"Madhya Pradesh"},"arunachal-pradesh":{"name":"Arunachal Pradesh"},"puducherry":{"name":"Puducherry"},"uttar-pradesh":{"name":"Uttar Pradesh"},"tamil-nadu":{"name":"Tamil Nadu"},"delhi":{"name":"Delhi"},"chhattisgarh":{"name":"Chhattisgarh"},"maharashtra":{"name":"Maharashtra"},"gujarat":{"name":"Gujarat"},"mizoram":{"name":"Mizoram"},"punjab":{"name":"Punjab"},"tripura":{"name":"Tripura"},"the-dadra-and-nagar-haveli-and-daman-and-diu":{"name":"The Dadra And Nagar Haveli And Daman And Diu"},"nagaland":{"name":"Nagaland"},"meghalaya":{"name":"Meghalaya"},"lakshadweep":{"name":"Lakshadweep"},"karnataka":{"name":"Karnataka"},"jharkhand":{"name":"Jharkhand"},"sikkim":{"name":"Sikkim"},"rajasthan":{"name":"Rajasthan"},"haryana":{"name":"Haryana"},"telangana":{"name":"Telangana"},"goa":{"name":"Goa"},"andaman-and-nicobar-islands":{"name":"Andaman And Nicobar Islands"},"bihar":{"name":"Bihar"},"jammu-and-kashmir":{"name":"Jammu And Kashmir"},"uttarakhand":{"name":"Uttarakhand"},"west-bengal":{"name":"West Bengal"},"odisha":{"name":"Odisha"},"kerala":{"name":"Kerala"},"himachal-pradesh":{"name":"Himachal Pradesh"}}